{
  "docusaurus-plugin-content-docs": {
    "guide": {
      "path": "/guide",
      "versions": [
        {
          "name": "current",
          "label": "Next",
          "isLast": true,
          "path": "/guide",
          "mainDocId": "intro",
          "docs": [
            {
              "id": "intro",
              "path": "/guide/intro",
              "sidebar": "default"
            },
            {
              "id": "invoice",
              "path": "/guide/invoice"
            },
            {
              "id": "logistics",
              "path": "/guide/logistics"
            },
            {
              "id": "payment",
              "path": "/guide/payment",
              "sidebar": "default"
            },
            {
              "id": "payment-admin",
              "path": "/guide/payment-admin"
            }
          ],
          "draftIds": [],
          "sidebars": {
            "default": {
              "link": {
                "path": "/guide/intro",
                "label": "intro"
              }
            }
          }
        }
      ],
      "breadcrumbs": true
    },
    "tutorial": {
      "path": "/tutorial",
      "versions": [
        {
          "name": "current",
          "label": "Next",
          "isLast": true,
          "path": "/tutorial",
          "mainDocId": "test-folder/index",
          "docs": [
            {
              "id": "01-intro",
              "path": "/tutorial/01-intro",
              "sidebar": "default"
            },
            {
              "id": "intro",
              "path": "/tutorial/intro",
              "sidebar": "default"
            },
            {
              "id": "logistics",
              "path": "/tutorial/logistics",
              "sidebar": "default"
            },
            {
              "id": "payment",
              "path": "/tutorial/payment",
              "sidebar": "default"
            },
            {
              "id": "payment-admin",
              "path": "/tutorial/payment-admin",
              "sidebar": "default"
            },
            {
              "id": "test-folder/index",
              "path": "/tutorial/test-folder/",
              "sidebar": "default"
            },
            {
              "id": "test-folder/intro",
              "path": "/tutorial/test-folder/intro",
              "sidebar": "default"
            },
            {
              "id": "test-folder/test-folder-2/index",
              "path": "/tutorial/test-folder/test-folder-2/",
              "sidebar": "default"
            },
            {
              "id": "test-folder/test-folder-2/intro",
              "path": "/tutorial/test-folder/test-folder-2/intro",
              "sidebar": "default"
            }
          ],
          "draftIds": [],
          "sidebars": {
            "default": {
              "link": {
                "path": "/tutorial/test-folder/",
                "label": "第一層資料夾"
              }
            }
          }
        }
      ],
      "breadcrumbs": true
    }
  }
}